[
  {
    "id": 103007001,
    "step": 1,
    "speakType": 2,
    "waitTime": 0,
    "IdSpeaker": "NPC103",
    "cnSpeaker": "罗莎",
    "enSpeaker": "Rosa",
    "cnAction": "抱着拖把，语速发紧",
    "cnWords": "Brennan先生……我能帮什么忙吗？我现在就在拖地，我...我还要赶着去清理大堂...您知道的，周末客人多，地板总是很脏...",
    "enAction": "Holding mop, tight voice",
    "enWords": "Mr. Brennan... can I help you? I'm mopping... gotta clean the lobby... you know, busy weekend, dirty floors...",
    "next": "103007100/103007200/103007300",
    "script": "branches",
    "ParameterStr0": "你知道Webb的勒索生意吗？",
    "ParameterStr1": "询问Jimmy的情况",
    "ParameterStr2": "询问Vivian的情况",
    "ParameterInt0": 103007100,
    "ParameterInt1": 103007200,
    "ParameterInt2": 103007300,
    "videoEpisode": "EPI01",
    "videoLoop": "loop4",
    "videoScene": "rosa_007",
    "videoId": "103007001",
    "cnLocation": "Rosa储物间 - 11月5日中午",
    "enLocation": "RosaStorageRoom - November 5th, Noon"
  },
  {
    "id": 103007100,
    "step": 100,
    "speakType": 2,
    "waitTime": 0,
    "IdSpeaker": "NPC101",
    "cnSpeaker": "扎克·布伦南",
    "enSpeaker": "Zack Brennan",
    "cnAction": "剥开糖纸，语气平静",
    "cnWords": "你知道Webb的勒索生意吗？",
    "enAction": "Unwraps candy, calm tone",
    "enWords": "Do you know about Webb's extortion business?",
    "next": "103007101",
    "script": "",
    "videoEpisode": "EPI01",
    "videoLoop": "loop4",
    "videoScene": "rosa_007",
    "videoId": "103007100",
    "cnLocation": "Rosa储物间 - 11月5日中午",
    "enLocation": "RosaStorageRoom - November 5th, Noon"
  },
  {
    "id": 103007101,
    "step": 101,
    "speakType": 2,
    "waitTime": 0,
    "IdSpeaker": "NPC103",
    "cnSpeaker": "罗莎",
    "enSpeaker": "Rosa",
    "cnAction": "脸色发白，手里的拖把差点掉了",
    "cnWords": "什...什么？勒索？我...我不知道您在说什么！我只是个清洁工...我每天就是擦地拖地...我什么都不知道！真的！Brennan先生，我什么都不知道！",
    "enAction": "Face turns pale, almost drops mop",
    "enWords": "Wh... what? Extortion? I... I don't know what you're talking about! I'm just a cleaner... I just mop floors every day... I don't know anything! Really! Mr. Brennan, I don't know anything!",
    "keyInfoType": "identity",
    "keyInfoContent": "Rosa的身份是清洁工",
    "next": "103007102",
    "script": "",
    "videoEpisode": "EPI01",
    "videoLoop": "loop4",
    "videoScene": "rosa_007",
    "videoId": "103007101",
    "cnLocation": "Rosa储物间 - 11月5日中午",
    "enLocation": "RosaStorageRoom - November 5th, Noon"
  },
  {
    "id": 103007102,
    "step": 102,
    "speakType": 2,
    "waitTime": 0,
    "IdSpeaker": "NPC101",
    "cnSpeaker": "扎克·布伦南",
    "enSpeaker": "Zack Brennan",
    "cnAction": "把糖放进嘴里，语气温和",
    "cnWords": "好，我明白了。继续干活吧。",
    "enAction": "Puts candy in mouth, gentle tone",
    "enWords": "Okay, I understand. Get back to work.",
    "next": "103007199",
    "script": "",
    "videoEpisode": "EPI01",
    "videoLoop": "loop4",
    "videoScene": "rosa_007",
    "videoId": "103007102",
    "cnLocation": "Rosa储物间 - 11月5日中午",
    "enLocation": "RosaStorageRoom - November 5th, Noon"
  },
  {
    "id": 103007199,
    "step": 199,
    "speakType": 2,
    "waitTime": 0,
    "IdSpeaker": "NPC103",
    "cnSpeaker": "罗莎",
    "enSpeaker": "Rosa",
    "cnAction": "松了口气，连忙点头",
    "cnWords": "好...好的...谢谢您，Brennan先生...",
    "enAction": "Relieved, nods hastily",
    "enWords": "O... okay... thank you, Mr. Brennan...",
    "next": "",
    "script": "end",
    "videoEpisode": "EPI01",
    "videoLoop": "loop4",
    "videoScene": "rosa_007",
    "videoId": "103007199",
    "cnLocation": "Rosa储物间 - 11月5日中午",
    "enLocation": "RosaStorageRoom - November 5th, Noon"
  },
  {
    "id": 103007200,
    "step": 200,
    "speakType": 2,
    "waitTime": 0,
    "IdSpeaker": "NPC101",
    "cnSpeaker": "扎克·布伦南",
    "enSpeaker": "Zack Brennan",
    "cnAction": "",
    "cnWords": "放轻松。我只想问问Jimmy最近有没有什么异常。你每天跟他擦肩，应该比我清楚。",
    "enAction": "",
    "enWords": "Relax. Just asking about Jimmy. Any odd behavior? You see him daily, you'd know better than me.",
    "next": "103007201",
    "script": "",
    "videoEpisode": "EPI01",
    "videoLoop": "loop4",
    "videoScene": "rosa_007",
    "videoId": "103007200",
    "cnLocation": "Rosa储物间 - 11月5日中午",
    "enLocation": "RosaStorageRoom - November 5th, Noon"
  },
  {
    "id": 103007201,
    "step": 201,
    "speakType": 2,
    "waitTime": 0,
    "IdSpeaker": "NPC103",
    "cnSpeaker": "罗莎",
    "enSpeaker": "Rosa",
    "cnAction": "放下拖把，紧张地搓着手",
    "cnWords": "Jimmy？他...他平常话少得要命，我也忙着赶场，很少...很少跟他说话...不过……等一下，让我想想——",
    "enAction": "Drops mop, rubs hands nervously",
    "enWords": "Jimmy? He... implies barely speaks. I'm busy too, rarely... talk to him... But... wait, let me think -",
    "next": "103007202",
    "script": "",
    "videoEpisode": "EPI01",
    "videoLoop": "loop4",
    "videoScene": "rosa_007",
    "videoId": "103007201",
    "cnLocation": "Rosa储物间 - 11月5日中午",
    "enLocation": "RosaStorageRoom - November 5th, Noon"
  },
  {
    "id": 103007202,
    "step": 202,
    "speakType": 2,
    "waitTime": 0,
    "IdSpeaker": "NPC101",
    "cnSpeaker": "扎克·布伦南",
    "enSpeaker": "Zack Brennan",
    "cnAction": "剥开糖纸",
    "cnWords": "慢慢来，记忆这种东西比地板顽固。",
    "enAction": "Unwraps candy",
    "enWords": "Take your time. Memory is stubborn, unlike dirt.",
    "next": "103007203",
    "script": "",
    "videoEpisode": "EPI01",
    "videoLoop": "loop4",
    "videoScene": "rosa_007",
    "videoId": "103007202",
    "cnLocation": "Rosa储物间 - 11月5日中午",
    "enLocation": "RosaStorageRoom - November 5th, Noon"
  },
  {
    "id": 103007203,
    "step": 203,
    "speakType": 2,
    "waitTime": 0,
    "IdSpeaker": "NPC103",
    "cnSpeaker": "罗莎",
    "enSpeaker": "Rosa",
    "cnAction": "眼睛一亮，语速加快",
    "cnWords": "我记起来了！大概一周前...不，应该是五六天前...我在走廊擦墙...我正擦着呢，就看见Jimmy带了一个人进了Webb先生的会客室！",
    "enAction": "Eyes light up, speaks faster",
    "enWords": "I remember! About a week ago... no, 5-6 days. I was cleaning the hallway wall... I saw Jimmy taking someone into Mr. Webb's parlor!",
    "next": "103007204",
    "script": "",
    "videoEpisode": "EPI01",
    "videoLoop": "loop4",
    "videoScene": "rosa_007",
    "videoId": "103007203",
    "cnLocation": "Rosa储物间 - 11月5日中午",
    "enLocation": "RosaStorageRoom - November 5th, Noon"
  },
  {
    "id": 103007204,
    "step": 204,
    "speakType": 2,
    "waitTime": 0,
    "IdSpeaker": "NPC101",
    "cnSpeaker": "扎克·布伦南",
    "enSpeaker": "Zack Brennan",
    "cnAction": "把糖放进嘴里",
    "cnWords": "会客室，不是办公室？",
    "enAction": "Puts candy in mouth",
    "enWords": "Parlor, not office?",
    "next": "103007205",
    "script": "",
    "videoEpisode": "EPI01",
    "videoLoop": "loop4",
    "videoScene": "rosa_007",
    "videoId": "103007204",
    "cnLocation": "Rosa储物间 - 11月5日中午",
    "enLocation": "RosaStorageRoom - November 5th, Noon"
  },
  {
    "id": 103007205,
    "step": 205,
    "speakType": 2,
    "waitTime": 0,
    "IdSpeaker": "NPC103",
    "cnSpeaker": "罗莎",
    "enSpeaker": "Rosa",
    "cnAction": "连忙点头",
    "cnWords": "对对对！就是会客室！我当时还纳闷呢，那里没什么值钱的，重要的东西都在办公室嘛！",
    "enAction": "Nods hastily",
    "enWords": "Yes yes! Parlor! I wondered why there, nothing valuable. Important stuff is in the office!",
    "next": "103007206",
    "script": "",
    "videoEpisode": "EPI01",
    "videoLoop": "loop4",
    "videoScene": "rosa_007",
    "videoId": "103007205",
    "cnLocation": "Rosa储物间 - 11月5日中午",
    "enLocation": "RosaStorageRoom - November 5th, Noon"
  },
  {
    "id": 103007206,
    "step": 206,
    "speakType": 2,
    "waitTime": 0,
    "IdSpeaker": "NPC101",
    "cnSpeaker": "扎克·布伦南",
    "enSpeaker": "Zack Brennan",
    "cnAction": "叼着棒棒糖，耐心地",
    "cnWords": "他进去多久？",
    "enAction": "Patiently",
    "enWords": "How long was he inside?",
    "next": "103007207",
    "script": "",
    "videoEpisode": "EPI01",
    "videoLoop": "loop4",
    "videoScene": "rosa_007",
    "videoId": "103007206",
    "cnLocation": "Rosa储物间 - 11月5日中午",
    "enLocation": "RosaStorageRoom - November 5th, Noon"
  },
  {
    "id": 103007207,
    "step": 207,
    "speakType": 2,
    "waitTime": 0,
    "IdSpeaker": "NPC103",
    "cnSpeaker": "罗莎",
    "enSpeaker": "Rosa",
    "cnAction": "回忆",
    "cnWords": "不久，就两三分钟...他们就出来了...那个人穿得很板正，看着像是什么要员...但他出来的时候面色不太好看...阴沉沉的...",
    "enAction": "Recalling",
    "enWords": "Not long, 2-3 minutes... they came out... that person was dressed very formally, looked like some dignitary... but he looked unwell when he came out... gloomy...",
    "next": "103007208",
    "script": "",
    "videoEpisode": "EPI01",
    "videoLoop": "loop4",
    "videoScene": "rosa_007",
    "videoId": "103007207",
    "cnLocation": "Rosa储物间 - 11月5日中午",
    "enLocation": "RosaStorageRoom - November 5th, Noon"
  },
  {
    "id": 103007208,
    "step": 208,
    "speakType": 2,
    "waitTime": 0,
    "IdSpeaker": "NPC101",
    "cnSpeaker": "扎克·布伦南",
    "enSpeaker": "Zack Brennan",
    "cnAction": "把棒棒糖从一边嘴角移到另一边",
    "cnWords": "看见你了吗？",
    "enAction": "Moves lollipop",
    "enWords": "Did he see you?",
    "next": "103007209",
    "script": "",
    "videoEpisode": "EPI01",
    "videoLoop": "loop4",
    "videoScene": "rosa_007",
    "videoId": "103007208",
    "cnLocation": "Rosa储物间 - 11月5日中午",
    "enLocation": "RosaStorageRoom - November 5th, Noon"
  },
  {
    "id": 103007209,
    "step": 209,
    "speakType": 2,
    "waitTime": 0,
    "IdSpeaker": "NPC103",
    "cnSpeaker": "罗莎",
    "enSpeaker": "Rosa",
    "cnAction": "啰嗦地",
    "cnWords": "看到了...他愣了一下，对我挤出个笑——那个笑好僵...我还以为他要说什么，但最后就...就匆忙走了...走得很快...",
    "enAction": "Ramble",
    "enWords": "Saw me... froze, forced a smile - stiff smile... thought he'd speak, but just... rushed off... very fast...",
    "next": "103007210",
    "script": "",
    "videoEpisode": "EPI01",
    "videoLoop": "loop4",
    "videoScene": "rosa_007",
    "videoId": "103007209",
    "cnLocation": "Rosa储物间 - 11月5日中午",
    "enLocation": "RosaStorageRoom - November 5th, Noon"
  },
  {
    "id": 103007210,
    "step": 210,
    "speakType": 2,
    "waitTime": 0,
    "IdSpeaker": "NPC101",
    "cnSpeaker": "扎克·布伦南",
    "enSpeaker": "Zack Brennan",
    "cnAction": "吃了一颗糖",
    "cnWords": "之后呢？还出现过这种情况？",
    "enAction": "Eats candy",
    "enWords": "After that? Did it happen again?",
    "next": "103007211",
    "script": "",
    "videoEpisode": "EPI01",
    "videoLoop": "loop4",
    "videoScene": "rosa_007",
    "videoId": "103007210",
    "cnLocation": "Rosa储物间 - 11月5日中午",
    "enLocation": "RosaStorageRoom - November 5th, Noon"
  },
  {
    "id": 103007211,
    "step": 211,
    "speakType": 2,
    "waitTime": 0,
    "IdSpeaker": "NPC103",
    "cnSpeaker": "罗莎",
    "enSpeaker": "Rosa",
    "cnAction": "拼命摇头，声音变小",
    "cnWords": "没有……我就那一次看到...Brennan先生，我只是看见，人是他自己进去的...我真的...我只是在擦墙...我什么都没做...",
    "enAction": "Shakes head furiously, voice lowers",
    "enWords": "No... only that one time... Mr. Brennan, I just saw him go in... I really... I was just cleaning the wall... I did nothing...",
    "next": "103007500",
    "script": "",
    "videoEpisode": "EPI01",
    "videoLoop": "loop4",
    "videoScene": "rosa_007",
    "videoId": "103007211",
    "cnLocation": "Rosa储物间 - 11月5日中午",
    "enLocation": "RosaStorageRoom - November 5th, Noon"
  },
  {
    "id": 103007300,
    "step": 300,
    "speakType": 2,
    "waitTime": 0,
    "IdSpeaker": "NPC101",
    "cnSpeaker": "扎克·布伦南",
    "enSpeaker": "Zack Brennan",
    "cnAction": "",
    "cnWords": "除了Jimmy，Vivian最近怎么样？你有没有注意到什么？",
    "enAction": "",
    "enWords": "Besides Jimmy, how is Vivian lately? Noticed anything?",
    "next": "103007301",
    "script": "",
    "videoEpisode": "EPI01",
    "videoLoop": "loop4",
    "videoScene": "rosa_007",
    "videoId": "103007300",
    "cnLocation": "Rosa储物间 - 11月5日中午",
    "enLocation": "RosaStorageRoom - November 5th, Noon"
  },
  {
    "id": 103007301,
    "step": 301,
    "speakType": 2,
    "waitTime": 0,
    "IdSpeaker": "NPC103",
    "cnSpeaker": "罗莎",
    "enSpeaker": "Rosa",
    "cnAction": "压低声音",
    "cnWords": "Vivian小姐...她最近状态很不好。我好几次看见她在角落里偷偷抹眼泪...而且...",
    "enAction": "Lowers voice",
    "enWords": "Miss Vivian... she's been in a bad way. I've seen her crying in corners several times... and...",
    "next": "103007302",
    "script": "",
    "videoEpisode": "EPI01",
    "videoLoop": "loop4",
    "videoScene": "rosa_007",
    "videoId": "103007301",
    "cnLocation": "Rosa储物间 - 11月5日中午",
    "enLocation": "RosaStorageRoom - November 5th, Noon"
  },
  {
    "id": 103007302,
    "step": 302,
    "speakType": 2,
    "waitTime": 0,
    "IdSpeaker": "NPC101",
    "cnSpeaker": "扎克·布伦南",
    "enSpeaker": "Zack Brennan",
    "cnAction": "追问",
    "cnWords": "而且什么？特别是案发那晚。",
    "enAction": "Presses",
    "enWords": "And what? Especially on the night of the incident.",
    "next": "103007303",
    "script": "",
    "videoEpisode": "EPI01",
    "videoLoop": "loop4",
    "videoScene": "rosa_007",
    "videoId": "103007302",
    "cnLocation": "Rosa储物间 - 11月5日中午",
    "enLocation": "RosaStorageRoom - November 5th, Noon"
  },
  {
    "id": 103007303,
    "step": 303,
    "speakType": 2,
    "waitTime": 0,
    "IdSpeaker": "NPC103",
    "cnSpeaker": "罗莎",
    "enSpeaker": "Rosa",
    "cnAction": "左右张望，极其小声",
    "cnWords": "就是那晚！大概11点左右...我正准备去清理会客室门口的走廊...我看见Vivian小姐神情紧张地快步走过去。",
    "enAction": "Looks around, whispers very softly",
    "enWords": "That night! Around 11... I was about to clean the hall near the parlor... I saw Miss Vivian walking fast, looking very nervous.",
    "keyInfoType": "witness",
    "keyInfoContent": "Rosa看到Vivian在走廊紧张地走向会客室",
    "next": "103007304",
    "script": "get",
    "ParameterStr0": "TIM010",
    "videoEpisode": "EPI01",
    "videoLoop": "loop4",
    "videoScene": "rosa_007",
    "videoId": "103007303",
    "cnLocation": "Rosa储物间 - 11月5日中午",
    "enLocation": "RosaStorageRoom - November 5th, Noon"
  },
  {
    "id": 103007304,
    "step": 304,
    "speakType": 2,
    "waitTime": 0,
    "IdSpeaker": "NPC101",
    "cnSpeaker": "扎克·布伦南",
    "enSpeaker": "Zack Brennan",
    "cnAction": "皱眉",
    "cnWords": "又是会客室？她手里拿东西了吗？",
    "enAction": "Frowns",
    "enWords": "The parlor again? Was she holding anything?",
    "next": "103007305",
    "script": "",
    "videoEpisode": "EPI01",
    "videoLoop": "loop4",
    "videoScene": "rosa_007",
    "videoId": "103007304",
    "cnLocation": "Rosa储物间 - 11月5日中午",
    "enLocation": "RosaStorageRoom - November 5th, Noon"
  },
  {
    "id": 103007305,
    "step": 305,
    "speakType": 2,
    "waitTime": 0,
    "IdSpeaker": "NPC103",
    "cnSpeaker": "罗莎",
    "enSpeaker": "Rosa",
    "cnAction": "用力点头",
    "cnWords": "拿了！手里拿着个小包...看着不大，但她抓得很紧，像是怕摔了似的。她一看到我，马上把包往怀里藏，头也不回就进去了。",
    "enAction": "Nods vigorously",
    "enWords": "She was! Holding a small bag... didn't look big, but she gripped it tightly, like she was afraid to drop it. When she saw me, she hid the bag in her arms and rushed inside without looking back.",
    "next": "103007500",
    "script": "",
    "videoEpisode": "EPI01",
    "videoLoop": "loop4",
    "videoScene": "rosa_007",
    "videoId": "103007305",
    "cnLocation": "Rosa储物间 - 11月5日中午",
    "enLocation": "RosaStorageRoom - November 5th, Noon"
  },
  {
    "id": 103007500,
    "step": 500,
    "speakType": 2,
    "waitTime": 0,
    "IdSpeaker": "NPC101",
    "cnSpeaker": "扎克·布伦南",
    "enSpeaker": "Zack Brennan",
    "cnAction": "走近，语气真诚",
    "cnWords": "我知道了。你做得很好，Rosa。",
    "enAction": "Steps closer, sincere tone",
    "enWords": "I see. You did good, Rosa.",
    "next": "103007501",
    "script": "",
    "videoEpisode": "EPI01",
    "videoLoop": "loop4",
    "videoScene": "rosa_007",
    "videoId": "103007500",
    "cnLocation": "Rosa储物间 - 11月5日中午",
    "enLocation": "RosaStorageRoom - November 5th, Noon"
  },
  {
    "id": 103007501,
    "step": 501,
    "speakType": 2,
    "waitTime": 0,
    "IdSpeaker": "NPC103",
    "cnSpeaker": "罗莎",
    "enSpeaker": "Rosa",
    "cnAction": "眼眶泛红，语速更快了",
    "cnWords": "我、我不想惹麻烦...我只是个清洁工...我只希望我女儿能继续治病……医生说只要坚持用药...她就能慢慢好起来...但是药很贵...我必须保住这份工作...",
    "enAction": "Eyes red, speaking faster",
    "enWords": "I... I don't want trouble... just a cleaner... I just want my daughter to get treatment... Doctor said medicine helps... but it's expensive... I must keep this job...",
    "next": "103007550",
    "script": "",
    "videoEpisode": "EPI01",
    "videoLoop": "loop4",
    "videoScene": "rosa_007",
    "videoId": "103007501",
    "cnLocation": "Rosa储物间 - 11月5日中午",
    "enLocation": "RosaStorageRoom - November 5th, Noon"
  },
  {
    "id": 103007550,
    "step": 550,
    "speakType": 1,
    "waitTime": 0,
    "IdSpeaker": "NPC101",
    "cnSpeaker": "扎克·布伦南",
    "enSpeaker": "Zack Brennan",
    "cnAction": "",
    "cnWords": "",
    "enAction": "",
    "enWords": "",
    "next": "103007552/103007502",
    "script": "branches",
    "ParameterStr0": "为了手术费，你会做傻事吗？",
    "ParameterStr1": "好，继续说。",
    "ParameterStr2": "",
    "ParameterInt0": 103007552,
    "ParameterInt1": 103007502,
    "ParameterInt2": 0,
    "videoEpisode": "EPI01",
    "videoLoop": "loop4",
    "videoScene": "rosa_007",
    "videoId": "103007550",
    "cnLocation": "Rosa储物间 - 11月5日中午",
    "enLocation": "RosaStorageRoom - November 5th, Noon"
  },
  {
    "id": 103007552,
    "step": 552,
    "speakType": 2,
    "waitTime": 0,
    "IdSpeaker": "NPC101",
    "cnSpeaker": "扎克·布伦南",
    "enSpeaker": "Zack Brennan",
    "cnAction": "语气平静",
    "cnWords": "为了手术费，你会做傻事吗？",
    "enAction": "Calm tone",
    "enWords": "Would you do something foolish for the surgery fees?",
    "next": "103007551",
    "script": "",
    "ParameterStr0": "",
    "ParameterStr1": "",
    "ParameterStr2": "",
    "ParameterInt0": 0,
    "ParameterInt1": 0,
    "ParameterInt2": 0,
    "videoEpisode": "EPI01",
    "videoLoop": "loop4",
    "videoScene": "rosa_007",
    "videoId": "103007552",
    "cnLocation": "Rosa储物间 - 11月5日中午",
    "enLocation": "RosaStorageRoom - November 5th, Noon"
  },
  {
    "id": 103007551,
    "step": 551,
    "speakType": 2,
    "waitTime": 0,
    "IdSpeaker": "NPC103",
    "cnSpeaker": "罗莎",
    "enSpeaker": "Rosa",
    "cnAction": "声音哽咽，连连摇头",
    "cnWords": "不会的！Brennan先生...医生说她需要手术...手术费还差很多...我每天都在发愁...但我绝不会因此做坏事...我只想靠自己的双手养活她...",
    "enAction": "Voice choking, shaking head repeatedly",
    "enWords": "No! Mr. Brennan... the doctor said she needs surgery... still short on surgery fees... I worry every day... but I would never do bad things because of it... I just want to support her with my own hands...",
    "next": "103007502",
    "script": "get",
    "ParameterStr0": "",
    "ParameterStr1": "Event005",
    "ParameterStr2": "",
    "ParameterInt0": 0,
    "ParameterInt1": 0,
    "ParameterInt2": 0,
    "videoEpisode": "EPI01",
    "videoLoop": "loop4",
    "videoScene": "rosa_007",
    "videoId": "103007551",
    "cnLocation": "Rosa储物间 - 11月5日中午",
    "enLocation": "RosaStorageRoom - November 5th, Noon"
  },
  {
    "id": 103007502,
    "step": 502,
    "speakType": 2,
    "waitTime": 0,
    "IdSpeaker": "NPC103",
    "cnSpeaker": "罗莎",
    "enSpeaker": "Rosa",
    "cnAction": "",
    "cnWords": "Brennan先生，如果还有什么需要问的，我都会说实话，只求别让Morrison再吓我...他...他上次说要让我失业...如果我失业了，我女儿的药就买不起了...",
    "enAction": "",
    "enWords": "Mr. Brennan, I'll tell the truth if you ask more, just don't let Morrison scare me... he... he threatened to fire me... if I lose my job, I can't afford my daughter's meds...",
    "next": "103007503",
    "script": "",
    "videoEpisode": "EPI01",
    "videoLoop": "loop4",
    "videoScene": "rosa_007",
    "videoId": "103007502",
    "cnLocation": "Rosa储物间 - 11月5日中午",
    "enLocation": "RosaStorageRoom - November 5th, Noon"
  },
  {
    "id": 103007503,
    "step": 503,
    "speakType": 2,
    "waitTime": 0,
    "IdSpeaker": "NPC101",
    "cnSpeaker": "扎克·布伦南",
    "enSpeaker": "Zack Brennan",
    "cnAction": "语气温和但坚定",
    "cnWords": "我会处理Morrison。你专心把地拖干净就行。你女儿的事，不用担心。",
    "enAction": "Gentle but firm",
    "enWords": "I'll handle Morrison. Just focus on mopping. Don't worry about your daughter.",
    "next": "103007504",
    "script": "",
    "videoEpisode": "EPI01",
    "videoLoop": "loop4",
    "videoScene": "rosa_007",
    "videoId": "103007503",
    "cnLocation": "Rosa储物间 - 11月5日中午",
    "enLocation": "RosaStorageRoom - November 5th, Noon"
  },
  {
    "id": 103007504,
    "step": 504,
    "speakType": 2,
    "waitTime": 0,
    "IdSpeaker": "NPC103",
    "cnSpeaker": "罗莎",
    "enSpeaker": "Rosa",
    "cnAction": "松了口气，连忙点头",
    "cnWords": "谢谢您...谢谢您，Brennan先生...我...我一定好好工作...您...您也保重...那些人很危险...",
    "enAction": "Relieved, nods hastily",
    "enWords": "Thank you... thank you Mr. Brennan... I... I'll work hard... You... take care... those people are dangerous...",
    "next": "",
    "script": "end",
    "videoEpisode": "EPI01",
    "videoLoop": "loop4",
    "videoScene": "rosa_007",
    "videoId": "103007504",
    "cnLocation": "Rosa储物间 - 11月5日中午",
    "enLocation": "RosaStorageRoom - November 5th, Noon"
  }
]