[
  {
    "id": 207003001,
    "step": 1,
    "speakType": 2,
    "waitTime": 0,
    "IdSpeaker": "NPC207",
    "cnSpeaker": "伦纳德",
    "enSpeaker": "Leonard Ross",
    "Location": "",
    "cnAction": "站在柜台工位旁，目光先是扫过 Mickey，然后落在 Zack 身上，领带依然微歪",
    "cnWords": "布伦南先生。",
    "enAction": "",
    "enWords": "",
    "next": "207003002",
    "script": "",
    "ParameterStr0": "",
    "ParameterStr1": "",
    "ParameterStr2": "",
    "ParameterInt0": 0,
    "ParameterInt1": 0,
    "ParameterInt2": 0,
    "videoEpisode": "EPI02",
    "videoLoop": "loop3",
    "videoId": "207003001",
    "videoScene": "leonard_l3_lobby"
  },
  {
    "id": 207003002,
    "step": 2,
    "speakType": 2,
    "waitTime": 0,
    "IdSpeaker": "NPC207",
    "cnSpeaker": "伦纳德",
    "enSpeaker": "Leonard Ross",
    "Location": "",
    "cnAction": "",
    "cnWords": "我本来以为上次我已经解释得很清楚了，Frank先生的事，和本行没有任何关系。",
    "enAction": "",
    "enWords": "",
    "next": "207003003",
    "script": "",
    "ParameterStr0": "",
    "ParameterStr1": "",
    "ParameterStr2": "",
    "ParameterInt0": 0,
    "ParameterInt1": 0,
    "ParameterInt2": 0,
    "videoEpisode": "EPI02",
    "videoLoop": "loop3",
    "videoId": "207003002",
    "videoScene": "leonard_l3_lobby"
  },
  {
    "id": 207003003,
    "step": 3,
    "speakType": 3,
    "waitTime": 0,
    "IdSpeaker": "NPC201",
    "cnSpeaker": "扎克·布伦南",
    "enSpeaker": "Zack Brennan",
    "Location": "",
    "cnAction": "走近柜台，眼神锐利",
    "cnWords": "看来你恢复冷静了，Ross先生。",
    "enAction": "",
    "enWords": "",
    "next": "207003004",
    "script": "",
    "ParameterStr0": "",
    "ParameterStr1": "",
    "ParameterStr2": "",
    "ParameterInt0": 0,
    "ParameterInt1": 0,
    "ParameterInt2": 0,
    "videoEpisode": "EPI02",
    "videoLoop": "loop3",
    "videoId": "207003003",
    "videoScene": "leonard_l3_lobby"
  },
  {
    "id": 207003004,
    "step": 4,
    "speakType": 3,
    "waitTime": 0,
    "IdSpeaker": "NPC201",
    "cnSpeaker": "扎克·布伦南",
    "enSpeaker": "Zack Brennan",
    "Location": "",
    "cnAction": "",
    "cnWords": "上次你只给我看了你想让我看的东西。",
    "enAction": "",
    "enWords": "",
    "next": "207003005",
    "script": "",
    "ParameterStr0": "",
    "ParameterStr1": "",
    "ParameterStr2": "",
    "ParameterInt0": 0,
    "ParameterInt1": 0,
    "ParameterInt2": 0,
    "videoEpisode": "EPI02",
    "videoLoop": "loop3",
    "videoId": "207003004",
    "videoScene": "leonard_l3_lobby"
  },
  {
    "id": 207003005,
    "step": 5,
    "speakType": 3,
    "waitTime": 0,
    "IdSpeaker": "NPC201",
    "cnSpeaker": "扎克·布伦南",
    "enSpeaker": "Zack Brennan",
    "Location": "",
    "cnAction": "",
    "cnWords": "而这次，我带了能看所有东西的钥匙。",
    "enAction": "",
    "enWords": "",
    "next": "207003006",
    "script": "",
    "ParameterStr0": "",
    "ParameterStr1": "",
    "ParameterStr2": "",
    "ParameterInt0": 0,
    "ParameterInt1": 0,
    "ParameterInt2": 0,
    "videoEpisode": "EPI02",
    "videoLoop": "loop3",
    "videoId": "207003005",
    "videoScene": "leonard_l3_lobby"
  },
  {
    "id": 207003006,
    "step": 6,
    "speakType": 3,
    "waitTime": 0,
    "IdSpeaker": "NPC201",
    "cnSpeaker": "扎克·布伦南",
    "enSpeaker": "Zack Brennan",
    "Location": "",
    "cnAction": "将律令拍在柜台上，语气不带情绪",
    "cnWords": "Ross 先生，这是法院令状。现在，请允许我们查阅与 Frank Kowalski 相关的所有档案。",
    "enAction": "",
    "enWords": "",
    "next": "207003007",
    "script": "",
    "ParameterStr0": "",
    "ParameterStr1": "",
    "ParameterStr2": "",
    "ParameterInt0": 0,
    "ParameterInt1": 0,
    "ParameterInt2": 0,
    "videoEpisode": "EPI02",
    "videoLoop": "loop3",
    "videoId": "207003006",
    "videoScene": "leonard_l3_lobby"
  },
  {
    "id": 207003007,
    "step": 7,
    "speakType": 2,
    "waitTime": 0,
    "IdSpeaker": "NPC207",
    "cnSpeaker": "伦纳德",
    "enSpeaker": "Leonard Ross",
    "Location": "",
    "cnAction": "看了一眼律令，眼神中闪过一丝掩饰不住的惊讶，拇指压了压右袖口，强作镇定",
    "cnWords": "你……你是怎么拿到法官的签名的？",
    "enAction": "",
    "enWords": "",
    "next": "207003008",
    "script": "",
    "ParameterStr0": "",
    "ParameterStr1": "",
    "ParameterStr2": "",
    "ParameterInt0": 0,
    "ParameterInt1": 0,
    "ParameterInt2": 0,
    "videoEpisode": "EPI02",
    "videoLoop": "loop3",
    "videoId": "207003007",
    "videoScene": "leonard_l3_lobby"
  },
  {
    "id": 207003008,
    "step": 8,
    "speakType": 2,
    "waitTime": 0,
    "IdSpeaker": "NPC207",
    "cnSpeaker": "伦纳德",
    "enSpeaker": "Leonard Ross",
    "Location": "",
    "cnAction": "",
    "cnWords": "……不过，既然手续完整。档案室和本人的办公室，两位都可以进。本行尊重法律程序。",
    "enAction": "",
    "enWords": "",
    "next": "207003009",
    "script": "",
    "ParameterStr0": "",
    "ParameterStr1": "",
    "ParameterStr2": "",
    "ParameterInt0": 0,
    "ParameterInt1": 0,
    "ParameterInt2": 0,
    "videoEpisode": "EPI02",
    "videoLoop": "loop3",
    "videoId": "207003008",
    "videoScene": "leonard_l3_lobby"
  },
  {
    "id": 207003009,
    "step": 9,
    "speakType": 3,
    "waitTime": 0,
    "IdSpeaker": "NPC201",
    "cnSpeaker": "扎克·布伦南",
    "enSpeaker": "Zack Brennan",
    "Location": "",
    "cnAction": "微微冷笑，语调带着明显的压迫感",
    "cnWords": "既然如此，Ross 先生，那就请你把相关的文件一份不落地都准备好吧。",
    "enAction": "",
    "enWords": "",
    "next": "207003010",
    "script": "",
    "ParameterStr0": "",
    "ParameterStr1": "",
    "ParameterStr2": "",
    "ParameterInt0": 0,
    "ParameterInt1": 0,
    "ParameterInt2": 0,
    "videoEpisode": "EPI02",
    "videoLoop": "loop3",
    "videoId": "207003009",
    "videoScene": "leonard_l3_lobby"
  },
  {
    "id": 207003010,
    "step": 10,
    "speakType": 3,
    "waitTime": 0,
    "IdSpeaker": "NPC201",
    "cnSpeaker": "扎克·布伦南",
    "enSpeaker": "Zack Brennan",
    "Location": "",
    "cnAction": "",
    "cnWords": "希望贵行的流程，经得起仔细打量。",
    "enAction": "",
    "enWords": "",
    "next": "207003011",
    "script": "",
    "ParameterStr0": "",
    "ParameterStr1": "",
    "ParameterStr2": "",
    "ParameterInt0": 0,
    "ParameterInt1": 0,
    "ParameterInt2": 0,
    "videoEpisode": "EPI02",
    "videoLoop": "loop3",
    "videoId": "207003010",
    "videoScene": "leonard_l3_lobby"
  },
  {
    "id": 207003011,
    "step": 11,
    "speakType": 2,
    "waitTime": 0,
    "IdSpeaker": "NPC207",
    "cnSpeaker": "伦纳德",
    "enSpeaker": "Leonard Ross",
    "Location": "",
    "cnAction": "脸色微沉，咬着后槽牙",
    "cnWords": "……当然。",
    "enAction": "",
    "enWords": "",
    "next": "",
    "script": "branches",
    "ParameterStr0": ". 你刚刚只说了档案室和你的办公室，贵宾室呢？",
    "ParameterStr1": ". 你说内部档案和对客文件分开管理——什么意思？",
    "ParameterStr2": ". Frank 的贷款档案谁经手的？",
    "ParameterInt0": 207003012,
    "ParameterInt1": 207003019,
    "ParameterInt2": 207003031,
    "videoEpisode": "EPI02",
    "videoLoop": "loop3",
    "videoId": "207003011",
    "videoScene": "leonard_l3_lobby"
  },
  {
    "id": 207003012,
    "step": 12,
    "speakType": 3,
    "waitTime": 0,
    "IdSpeaker": "NPC201",
    "cnSpeaker": "扎克·布伦南",
    "enSpeaker": "Zack Brennan",
    "Location": "",
    "cnAction": "把律令往柜台沿轻轻一搁，没收回手，目光逼视着 Leonard",
    "cnWords": "你刚刚只说了档案室和你的办公室，贵宾室呢？",
    "enAction": "",
    "enWords": "",
    "next": "207003013",
    "script": "",
    "ParameterStr0": "",
    "ParameterStr1": "",
    "ParameterStr2": "",
    "ParameterInt0": 0,
    "ParameterInt1": 0,
    "ParameterInt2": 0,
    "videoEpisode": "EPI02",
    "videoLoop": "loop3",
    "videoId": "207003012",
    "videoScene": "leonard_l3_lobby"
  },
  {
    "id": 207003013,
    "step": 13,
    "speakType": 2,
    "waitTime": 0,
    "IdSpeaker": "NPC207",
    "cnSpeaker": "伦纳德",
    "enSpeaker": "Leonard Ross",
    "Location": "",
    "cnAction": "眼神不易察觉地一闪，拇指用力压了一下左袖口，声音低了半度",
    "cnWords": "贵宾室，它归 Moore 行长直接管理，有另一套档案规章。那部分需要和他另行确认。不是拒绝，是程序。",
    "enAction": "",
    "enWords": "",
    "next": "207003014",
    "script": "",
    "ParameterStr0": "",
    "ParameterStr1": "",
    "ParameterStr2": "",
    "ParameterInt0": 0,
    "ParameterInt1": 0,
    "ParameterInt2": 0,
    "videoEpisode": "EPI02",
    "videoLoop": "loop3",
    "videoId": "207003013",
    "videoScene": "leonard_l3_lobby"
  },
  {
    "id": 207003014,
    "step": 14,
    "speakType": 3,
    "waitTime": 0,
    "IdSpeaker": "NPC201",
    "cnSpeaker": "扎克·布伦南",
    "enSpeaker": "Zack Brennan",
    "Location": "",
    "cnAction": "",
    "cnWords": "贵宾室里有什么档案。",
    "enAction": "",
    "enWords": "",
    "next": "207003015",
    "script": "",
    "ParameterStr0": "",
    "ParameterStr1": "",
    "ParameterStr2": "",
    "ParameterInt0": 0,
    "ParameterInt1": 0,
    "ParameterInt2": 0,
    "videoEpisode": "EPI02",
    "videoLoop": "loop3",
    "videoId": "207003014",
    "videoScene": "leonard_l3_lobby"
  },
  {
    "id": 207003015,
    "step": 15,
    "speakType": 2,
    "waitTime": 0,
    "IdSpeaker": "NPC207",
    "cnSpeaker": "伦纳德",
    "enSpeaker": "Leonard Ross",
    "Location": "",
    "cnAction": "",
    "cnWords": "特殊客户的往来记录。",
    "enAction": "",
    "enWords": "",
    "next": "207003016",
    "script": "",
    "ParameterStr0": "",
    "ParameterStr1": "",
    "ParameterStr2": "",
    "ParameterInt0": 0,
    "ParameterInt1": 0,
    "ParameterInt2": 0,
    "videoEpisode": "EPI02",
    "videoLoop": "loop3",
    "videoId": "207003015",
    "videoScene": "leonard_l3_lobby"
  },
  {
    "id": 207003016,
    "step": 16,
    "speakType": 2,
    "waitTime": 0,
    "IdSpeaker": "NPC207",
    "cnSpeaker": "伦纳德",
    "enSpeaker": "Leonard Ross",
    "Location": "",
    "cnAction": "",
    "cnWords": "客户隐私规章覆盖那一层，我无权越过 Moore 行长单独决定。您要进那个区域，得找他谈。",
    "enAction": "",
    "enWords": "",
    "next": "207003017",
    "script": "",
    "ParameterStr0": "",
    "ParameterStr1": "",
    "ParameterStr2": "",
    "ParameterInt0": 0,
    "ParameterInt1": 0,
    "ParameterInt2": 0,
    "videoEpisode": "EPI02",
    "videoLoop": "loop3",
    "videoId": "207003016",
    "videoScene": "leonard_l3_lobby"
  },
  {
    "id": 207003017,
    "step": 17,
    "speakType": 3,
    "waitTime": 0,
    "IdSpeaker": "NPC201",
    "cnSpeaker": "扎克·布伦南",
    "enSpeaker": "Zack Brennan",
    "Location": "",
    "cnAction": "",
    "cnWords": "Moore 今天在？",
    "enAction": "",
    "enWords": "",
    "next": "207003018",
    "script": "",
    "ParameterStr0": "",
    "ParameterStr1": "",
    "ParameterStr2": "",
    "ParameterInt0": 0,
    "ParameterInt1": 0,
    "ParameterInt2": 0,
    "videoEpisode": "EPI02",
    "videoLoop": "loop3",
    "videoId": "207003017",
    "videoScene": "leonard_l3_lobby"
  },
  {
    "id": 207003018,
    "step": 18,
    "speakType": 2,
    "waitTime": 0,
    "IdSpeaker": "NPC207",
    "cnSpeaker": "伦纳德",
    "enSpeaker": "Leonard Ross",
    "Location": "",
    "cnAction": "",
    "cnWords": "如果他愿意见你的话，他就在。",
    "enAction": "",
    "enWords": "",
    "next": "207003011",
    "script": "",
    "ParameterStr0": "",
    "ParameterStr1": "",
    "ParameterStr2": "",
    "ParameterInt0": 0,
    "ParameterInt1": 0,
    "ParameterInt2": 0,
    "videoEpisode": "EPI02",
    "videoLoop": "loop3",
    "videoId": "207003018",
    "videoScene": "leonard_l3_lobby"
  },
  {
    "id": 207003019,
    "step": 19,
    "speakType": 3,
    "waitTime": 0,
    "IdSpeaker": "NPC201",
    "cnSpeaker": "扎克·布伦南",
    "enSpeaker": "Zack Brennan",
    "Location": "",
    "cnAction": "盯着 Leonard 那条歪着的领带，又抬眼",
    "cnWords": "你说内部档案和对客文件分开管理——什么意思？上次你给我看的账户摘要，是哪一种？",
    "enAction": "",
    "enWords": "",
    "next": "207003020",
    "script": "",
    "ParameterStr0": "",
    "ParameterStr1": "",
    "ParameterStr2": "",
    "ParameterInt0": 0,
    "ParameterInt1": 0,
    "ParameterInt2": 0,
    "videoEpisode": "EPI02",
    "videoLoop": "loop3",
    "videoId": "207003019",
    "videoScene": "leonard_l3_lobby"
  },
  {
    "id": 207003020,
    "step": 20,
    "speakType": 2,
    "waitTime": 0,
    "IdSpeaker": "NPC207",
    "cnSpeaker": "伦纳德",
    "enSpeaker": "Leonard Ross",
    "Location": "",
    "cnAction": "语速稍微变快，像是在背诵条款",
    "cnWords": "上次给您看的是对客版本。本行的内部档案和对客文件是分开管理的。",
    "enAction": "",
    "enWords": "",
    "next": "207003021",
    "script": "",
    "ParameterStr0": "",
    "ParameterStr1": "",
    "ParameterStr2": "",
    "ParameterInt0": 0,
    "ParameterInt1": 0,
    "ParameterInt2": 0,
    "videoEpisode": "EPI02",
    "videoLoop": "loop3",
    "videoId": "207003020",
    "videoScene": "leonard_l3_lobby"
  },
  {
    "id": 207003021,
    "step": 21,
    "speakType": 2,
    "waitTime": 0,
    "IdSpeaker": "NPC207",
    "cnSpeaker": "伦纳德",
    "enSpeaker": "Leonard Ross",
    "Location": "",
    "cnAction": "",
    "cnWords": "内部存档和寄给客户的版本，在格式上可能存在差异。这属于归档流程，不影响数字准确。",
    "enAction": "",
    "enWords": "",
    "next": "207003022",
    "script": "",
    "ParameterStr0": "",
    "ParameterStr1": "",
    "ParameterStr2": "",
    "ParameterInt0": 0,
    "ParameterInt1": 0,
    "ParameterInt2": 0,
    "videoEpisode": "EPI02",
    "videoLoop": "loop3",
    "videoId": "207003021",
    "videoScene": "leonard_l3_lobby"
  },
  {
    "id": 207003022,
    "step": 22,
    "speakType": 3,
    "waitTime": 0,
    "IdSpeaker": "NPC201",
    "cnSpeaker": "扎克·布伦南",
    "enSpeaker": "Zack Brennan",
    "Location": "",
    "cnAction": "",
    "cnWords": "所以寄给客户的版本，和你们存档的，不一定一样。",
    "enAction": "",
    "enWords": "",
    "next": "207003023",
    "script": "",
    "ParameterStr0": "",
    "ParameterStr1": "",
    "ParameterStr2": "",
    "ParameterInt0": 0,
    "ParameterInt1": 0,
    "ParameterInt2": 0,
    "videoEpisode": "EPI02",
    "videoLoop": "loop3",
    "videoId": "207003022",
    "videoScene": "leonard_l3_lobby"
  },
  {
    "id": 207003023,
    "step": 23,
    "speakType": 2,
    "waitTime": 0,
    "IdSpeaker": "NPC207",
    "cnSpeaker": "伦纳德",
    "enSpeaker": "Leonard Ross",
    "Location": "",
    "cnAction": "",
    "cnWords": "格式层面，是有可能的。",
    "enAction": "",
    "enWords": "",
    "next": "207003024",
    "script": "",
    "ParameterStr0": "",
    "ParameterStr1": "",
    "ParameterStr2": "",
    "ParameterInt0": 0,
    "ParameterInt1": 0,
    "ParameterInt2": 0,
    "videoEpisode": "EPI02",
    "videoLoop": "loop3",
    "videoId": "207003023",
    "videoScene": "leonard_l3_lobby"
  },
  {
    "id": 207003024,
    "step": 24,
    "speakType": 2,
    "waitTime": 0,
    "IdSpeaker": "NPC207",
    "cnSpeaker": "伦纳德",
    "enSpeaker": "Leonard Ross",
    "Location": "",
    "cnAction": "",
    "cnWords": "数字准确。格式归格式。",
    "enAction": "",
    "enWords": "",
    "next": "207003025",
    "script": "get",
    "ParameterStr0": "2073001",
    "ParameterStr1": "",
    "ParameterStr2": "",
    "ParameterInt0": 0,
    "ParameterInt1": 0,
    "ParameterInt2": 0,
    "videoEpisode": "EPI02",
    "videoLoop": "loop3",
    "videoId": "207003024",
    "videoScene": "leonard_l3_lobby"
  },
  {
    "id": 207003025,
    "step": 25,
    "speakType": 3,
    "waitTime": 0,
    "IdSpeaker": "NPC201",
    "cnSpeaker": "扎克·布伦南",
    "enSpeaker": "Zack Brennan",
    "Location": "",
    "cnAction": "",
    "cnWords": "客户拿到的对账单，页眉写的是什么。",
    "enAction": "",
    "enWords": "",
    "next": "207003026",
    "script": "",
    "ParameterStr0": "",
    "ParameterStr1": "",
    "ParameterStr2": "",
    "ParameterInt0": 0,
    "ParameterInt1": 0,
    "ParameterInt2": 0,
    "videoEpisode": "EPI02",
    "videoLoop": "loop3",
    "videoId": "207003025",
    "videoScene": "leonard_l3_lobby"
  },
  {
    "id": 207003026,
    "step": 26,
    "speakType": 2,
    "waitTime": 0,
    "IdSpeaker": "NPC207",
    "cnSpeaker": "伦纳德",
    "enSpeaker": "Leonard Ross",
    "Location": "",
    "cnAction": "",
    "cnWords": "看账户类型。",
    "enAction": "",
    "enWords": "",
    "next": "207003027",
    "script": "",
    "ParameterStr0": "",
    "ParameterStr1": "",
    "ParameterStr2": "",
    "ParameterInt0": 0,
    "ParameterInt1": 0,
    "ParameterInt2": 0,
    "videoEpisode": "EPI02",
    "videoLoop": "loop3",
    "videoId": "207003026",
    "videoScene": "leonard_l3_lobby"
  },
  {
    "id": 207003027,
    "step": 27,
    "speakType": 2,
    "waitTime": 0,
    "IdSpeaker": "NPC207",
    "cnSpeaker": "伦纳德",
    "enSpeaker": "Leonard Ross",
    "Location": "",
    "cnAction": "",
    "cnWords": "有些客户的对账单通过关联机构代发，页眉会对应不同抬头。这是联合运营模式，行内有规范。",
    "enAction": "",
    "enWords": "",
    "next": "207003028",
    "script": "",
    "ParameterStr0": "",
    "ParameterStr1": "",
    "ParameterStr2": "",
    "ParameterInt0": 0,
    "ParameterInt1": 0,
    "ParameterInt2": 0,
    "videoEpisode": "EPI02",
    "videoLoop": "loop3",
    "videoId": "207003027",
    "videoScene": "leonard_l3_lobby"
  },
  {
    "id": 207003028,
    "step": 28,
    "speakType": 3,
    "waitTime": 0,
    "IdSpeaker": "NPC201",
    "cnSpeaker": "扎克·布伦南",
    "enSpeaker": "Zack Brennan",
    "Location": "",
    "cnAction": "",
    "cnWords": "关联机构。",
    "enAction": "",
    "enWords": "",
    "next": "207003029",
    "script": "",
    "ParameterStr0": "",
    "ParameterStr1": "",
    "ParameterStr2": "",
    "ParameterInt0": 0,
    "ParameterInt1": 0,
    "ParameterInt2": 0,
    "videoEpisode": "EPI02",
    "videoLoop": "loop3",
    "videoId": "207003028",
    "videoScene": "leonard_l3_lobby"
  },
  {
    "id": 207003029,
    "step": 29,
    "speakType": 2,
    "waitTime": 0,
    "IdSpeaker": "NPC207",
    "cnSpeaker": "伦纳德",
    "enSpeaker": "Leonard Ross",
    "Location": "",
    "cnAction": "",
    "cnWords": "贷款类账户的结构，Moore 行长那边会有完整说明。",
    "enAction": "",
    "enWords": "",
    "next": "207003030",
    "script": "",
    "ParameterStr0": "",
    "ParameterStr1": "",
    "ParameterStr2": "",
    "ParameterInt0": 0,
    "ParameterInt1": 0,
    "ParameterInt2": 0,
    "videoEpisode": "EPI02",
    "videoLoop": "loop3",
    "videoId": "207003029",
    "videoScene": "leonard_l3_lobby"
  },
  {
    "id": 207003030,
    "step": 30,
    "speakType": 2,
    "waitTime": 0,
    "IdSpeaker": "NPC207",
    "cnSpeaker": "伦纳德",
    "enSpeaker": "Leonard Ross",
    "Location": "",
    "cnAction": "",
    "cnWords": "档案里也有。您可以自己看。",
    "enAction": "",
    "enWords": "",
    "next": "207003011",
    "script": "",
    "ParameterStr0": "",
    "ParameterStr1": "",
    "ParameterStr2": "",
    "ParameterInt0": 0,
    "ParameterInt1": 0,
    "ParameterInt2": 0,
    "videoEpisode": "EPI02",
    "videoLoop": "loop3",
    "videoId": "207003030",
    "videoScene": "leonard_l3_lobby"
  },
  {
    "id": 207003031,
    "step": 31,
    "speakType": 3,
    "waitTime": 0,
    "IdSpeaker": "NPC201",
    "cnSpeaker": "扎克·布伦南",
    "enSpeaker": "Zack Brennan",
    "Location": "",
    "cnAction": "把律令折起一角，放在柜台上，盯着他的眼睛",
    "cnWords": "Frank 的贷款档案谁经手的？你上次可是信誓旦旦地说，你是他的贷款专员，负责这个账户三年了。",
    "enAction": "",
    "enWords": "",
    "next": "207003032",
    "script": "",
    "ParameterStr0": "",
    "ParameterStr1": "",
    "ParameterStr2": "",
    "ParameterInt0": 0,
    "ParameterInt1": 0,
    "ParameterInt2": 0,
    "videoEpisode": "EPI02",
    "videoLoop": "loop3",
    "videoId": "207003031",
    "videoScene": "leonard_l3_lobby"
  },
  {
    "id": 207003032,
    "step": 32,
    "speakType": 2,
    "waitTime": 0,
    "IdSpeaker": "NPC207",
    "cnSpeaker": "伦纳德",
    "enSpeaker": "Leonard Ross",
    "Location": "",
    "cnAction": "避开了 Zack 的视线，看着桌面的登记簿",
    "cnWords": "常规跟进是我负责。但特殊客户的贷款档案，由 Moore 行长亲自负责。",
    "enAction": "",
    "enWords": "",
    "next": "207003033",
    "script": "",
    "ParameterStr0": "",
    "ParameterStr1": "",
    "ParameterStr2": "",
    "ParameterInt0": 0,
    "ParameterInt1": 0,
    "ParameterInt2": 0,
    "videoEpisode": "EPI02",
    "videoLoop": "loop3",
    "videoId": "207003032",
    "videoScene": "leonard_l3_lobby"
  },
  {
    "id": 207003033,
    "step": 33,
    "speakType": 2,
    "waitTime": 0,
    "IdSpeaker": "NPC207",
    "cnSpeaker": "伦纳德",
    "enSpeaker": "Leonard Ross",
    "Location": "",
    "cnAction": "",
    "cnWords": "这个分类下的账户，统一归他管。",
    "enAction": "",
    "enWords": "",
    "next": "207003034",
    "script": "",
    "ParameterStr0": "",
    "ParameterStr1": "",
    "ParameterStr2": "",
    "ParameterInt0": 0,
    "ParameterInt1": 0,
    "ParameterInt2": 0,
    "videoEpisode": "EPI02",
    "videoLoop": "loop3",
    "videoId": "207003033",
    "videoScene": "leonard_l3_lobby"
  },
  {
    "id": 207003034,
    "step": 34,
    "speakType": 3,
    "waitTime": 0,
    "IdSpeaker": "NPC201",
    "cnSpeaker": "扎克·布伦南",
    "enSpeaker": "Zack Brennan",
    "Location": "",
    "cnAction": "",
    "cnWords": "那你在这个案子里参与了什么。还是说，你的工作仅仅是替银行跟外面那些“催债人”打交道？",
    "enAction": "",
    "enWords": "",
    "next": "207003035",
    "script": "",
    "ParameterStr0": "",
    "ParameterStr1": "",
    "ParameterStr2": "",
    "ParameterInt0": 0,
    "ParameterInt1": 0,
    "ParameterInt2": 0,
    "videoEpisode": "EPI02",
    "videoLoop": "loop3",
    "videoId": "207003034",
    "videoScene": "leonard_l3_lobby"
  },
  {
    "id": 207003035,
    "step": 35,
    "speakType": 2,
    "waitTime": 0,
    "IdSpeaker": "NPC207",
    "cnSpeaker": "伦纳德",
    "enSpeaker": "Leonard Ross",
    "Location": "",
    "cnAction": "猛地抬起头，语气冷硬了几分，带着明显的抗拒",
    "cnWords": "布伦南先生，我上次就说过，我不认识什么催债的人。",
    "enAction": "",
    "enWords": "",
    "next": "207003036",
    "script": "",
    "ParameterStr0": "",
    "ParameterStr1": "",
    "ParameterStr2": "",
    "ParameterInt0": 0,
    "ParameterInt1": 0,
    "ParameterInt2": 0,
    "videoEpisode": "EPI02",
    "videoLoop": "loop3",
    "videoId": "207003035",
    "videoScene": "leonard_l3_lobby"
  },
  {
    "id": 207003036,
    "step": 36,
    "speakType": 3,
    "waitTime": 0,
    "IdSpeaker": "NPC201",
    "cnSpeaker": "扎克·布伦南",
    "enSpeaker": "Zack Brennan",
    "Location": "",
    "cnAction": "",
    "cnWords": "行，你说了算。",
    "enAction": "",
    "enWords": "",
    "next": "207003037",
    "script": "",
    "ParameterStr0": "",
    "ParameterStr1": "",
    "ParameterStr2": "",
    "ParameterInt0": 0,
    "ParameterInt1": 0,
    "ParameterInt2": 0,
    "videoEpisode": "EPI02",
    "videoLoop": "loop3",
    "videoId": "207003036",
    "videoScene": "leonard_l3_lobby"
  },
  {
    "id": 207003037,
    "step": 37,
    "speakType": 2,
    "waitTime": 0,
    "IdSpeaker": "NPC207",
    "cnSpeaker": "伦纳德",
    "enSpeaker": "Leonard Ross",
    "Location": "",
    "cnAction": "",
    "cnWords": "我的工作仅限于银行内部。比如，协议文书由我代填。",
    "enAction": "",
    "enWords": "",
    "next": "207003038",
    "script": "",
    "ParameterStr0": "",
    "ParameterStr1": "",
    "ParameterStr2": "",
    "ParameterInt0": 0,
    "ParameterInt1": 0,
    "ParameterInt2": 0,
    "videoEpisode": "EPI02",
    "videoLoop": "loop3",
    "videoId": "207003037",
    "videoScene": "leonard_l3_lobby"
  },
  {
    "id": 207003038,
    "step": 38,
    "speakType": 2,
    "waitTime": 0,
    "IdSpeaker": "NPC207",
    "cnSpeaker": "伦纳德",
    "enSpeaker": "Leonard Ross",
    "Location": "",
    "cnAction": "",
    "cnWords": "Kowalski 先生当时做过口头确认。这符合本行流程。",
    "enAction": "",
    "enWords": "",
    "next": "207003039",
    "script": "",
    "ParameterStr0": "",
    "ParameterStr1": "",
    "ParameterStr2": "",
    "ParameterInt0": 0,
    "ParameterInt1": 0,
    "ParameterInt2": 0,
    "videoEpisode": "EPI02",
    "videoLoop": "loop3",
    "videoId": "207003038",
    "videoScene": "leonard_l3_lobby"
  },
  {
    "id": 207003039,
    "step": 39,
    "speakType": 3,
    "waitTime": 0,
    "IdSpeaker": "NPC201",
    "cnSpeaker": "扎克·布伦南",
    "enSpeaker": "Zack Brennan",
    "Location": "",
    "cnAction": "",
    "cnWords": "没有书面签名吗。",
    "enAction": "",
    "enWords": "",
    "next": "207003040",
    "script": "",
    "ParameterStr0": "",
    "ParameterStr1": "",
    "ParameterStr2": "",
    "ParameterInt0": 0,
    "ParameterInt1": 0,
    "ParameterInt2": 0,
    "videoEpisode": "EPI02",
    "videoLoop": "loop3",
    "videoId": "207003039",
    "videoScene": "leonard_l3_lobby"
  },
  {
    "id": 207003040,
    "step": 40,
    "speakType": 2,
    "waitTime": 0,
    "IdSpeaker": "NPC207",
    "cnSpeaker": "伦纳德",
    "enSpeaker": "Leonard Ross",
    "Location": "",
    "cnAction": "",
    "cnWords": "这类贷款在本行有口头确认的先例。",
    "enAction": "",
    "enWords": "",
    "next": "207003041",
    "script": "",
    "ParameterStr0": "",
    "ParameterStr1": "",
    "ParameterStr2": "",
    "ParameterInt0": 0,
    "ParameterInt1": 0,
    "ParameterInt2": 0,
    "videoEpisode": "EPI02",
    "videoLoop": "loop3",
    "videoId": "207003040",
    "videoScene": "leonard_l3_lobby"
  },
  {
    "id": 207003041,
    "step": 41,
    "speakType": 2,
    "waitTime": 0,
    "IdSpeaker": "NPC207",
    "cnSpeaker": "伦纳德",
    "enSpeaker": "Leonard Ross",
    "Location": "",
    "cnAction": "",
    "cnWords": "程序走过，就不算空白。",
    "enAction": "",
    "enWords": "",
    "next": "207003042",
    "script": "",
    "ParameterStr0": "",
    "ParameterStr1": "",
    "ParameterStr2": "",
    "ParameterInt0": 0,
    "ParameterInt1": 0,
    "ParameterInt2": 0,
    "videoEpisode": "EPI02",
    "videoLoop": "loop3",
    "videoId": "207003041",
    "videoScene": "leonard_l3_lobby"
  },
  {
    "id": 207003042,
    "step": 42,
    "speakType": 3,
    "waitTime": 0,
    "IdSpeaker": "NPC201",
    "cnSpeaker": "扎克·布伦南",
    "enSpeaker": "Zack Brennan",
    "Location": "",
    "cnAction": "",
    "cnWords": "档案里有记录口头确认的时间和在场人吗。",
    "enAction": "",
    "enWords": "",
    "next": "207003043",
    "script": "",
    "ParameterStr0": "",
    "ParameterStr1": "",
    "ParameterStr2": "",
    "ParameterInt0": 0,
    "ParameterInt1": 0,
    "ParameterInt2": 0,
    "videoEpisode": "EPI02",
    "videoLoop": "loop3",
    "videoId": "207003042",
    "videoScene": "leonard_l3_lobby"
  },
  {
    "id": 207003043,
    "step": 43,
    "speakType": 2,
    "waitTime": 0,
    "IdSpeaker": "NPC207",
    "cnSpeaker": "伦纳德",
    "enSpeaker": "Leonard Ross",
    "Location": "",
    "cnAction": "",
    "cnWords": "档案室里会有记录。",
    "enAction": "",
    "enWords": "",
    "next": "207003044",
    "script": "",
    "ParameterStr0": "",
    "ParameterStr1": "",
    "ParameterStr2": "",
    "ParameterInt0": 0,
    "ParameterInt1": 0,
    "ParameterInt2": 0,
    "videoEpisode": "EPI02",
    "videoLoop": "loop3",
    "videoId": "207003043",
    "videoScene": "leonard_l3_lobby"
  },
  {
    "id": 207003044,
    "step": 44,
    "speakType": 2,
    "waitTime": 0,
    "IdSpeaker": "NPC207",
    "cnSpeaker": "伦纳德",
    "enSpeaker": "Leonard Ross",
    "Location": "",
    "cnAction": "",
    "cnWords": "您进去看，比我在这里复述更清楚。",
    "enAction": "",
    "enWords": "",
    "next": "207003045",
    "script": "",
    "ParameterStr0": "",
    "ParameterStr1": "",
    "ParameterStr2": "",
    "ParameterInt0": 0,
    "ParameterInt1": 0,
    "ParameterInt2": 0,
    "videoEpisode": "EPI02",
    "videoLoop": "loop3",
    "videoId": "207003044",
    "videoScene": "leonard_l3_lobby"
  },
  {
    "id": 207003045,
    "step": 45,
    "speakType": 2,
    "waitTime": 0,
    "IdSpeaker": "NPC207",
    "cnSpeaker": "伦纳德",
    "enSpeaker": "Leonard Ross",
    "Location": "",
    "cnAction": "似乎急于结束这场对话",
    "cnWords": "档案室的钥匙我让助理去拿，五分钟内给您。",
    "enAction": "",
    "enWords": "",
    "next": "207003046",
    "script": "",
    "ParameterStr0": "",
    "ParameterStr1": "",
    "ParameterStr2": "",
    "ParameterInt0": 0,
    "ParameterInt1": 0,
    "ParameterInt2": 0,
    "videoEpisode": "EPI02",
    "videoLoop": "loop3",
    "videoId": "207003045",
    "videoScene": "leonard_l3_lobby"
  },
  {
    "id": 207003046,
    "step": 46,
    "speakType": 2,
    "waitTime": 0,
    "IdSpeaker": "NPC207",
    "cnSpeaker": "伦纳德",
    "enSpeaker": "Leonard Ross",
    "Location": "",
    "cnAction": "",
    "cnWords": "贵宾室的事，请和 Moore 行长谈。他在里面等着您。",
    "enAction": "",
    "enWords": "",
    "next": "",
    "script": "end",
    "ParameterStr0": "",
    "ParameterStr1": "",
    "ParameterStr2": "",
    "ParameterInt0": 0,
    "ParameterInt1": 0,
    "ParameterInt2": 0,
    "videoEpisode": "EPI02",
    "videoLoop": "loop3",
    "videoId": "207003046",
    "videoScene": "leonard_l3_lobby"
  }
]
